score.cli-0.4.4-py3.7-nspkg.pth
score/cli/__init__.py
score/cli/cli.py
score/cli/clibase.py
score/cli/conf.py
score.cli-0.4.4.dist-info/COPYING.LESSER.txt
score.cli-0.4.4.dist-info/METADATA
score.cli-0.4.4.dist-info/WHEEL
score.cli-0.4.4.dist-info/entry_points.txt
score.cli-0.4.4.dist-info/namespace_packages.txt
score.cli-0.4.4.dist-info/top_level.txt
score.cli-0.4.4.dist-info/RECORD
